pytessng/Config.py
pytessng/GlobalVar.py
pytessng/Logger.py
pytessng/ProgressDialog.py
pytessng/__init__.py
pytessng/Files/Cert/JidaTraffic_key
pytessng/Files/Doc/PYTESSNG导入导出数据格式.docx
pytessng/Files/Doc/PYTESSNG导入导出数据格式.pdf
pytessng/Files/Doc/PYTESSNG用户使用手册.pdf
pytessng/Files/Doc/Tessng.pyi
pytessng/Files/Doc/startPage.html
pytessng/Files/Doc/version.json
pytessng/Files/Examples/1-路网导入样例：OpenDrive/上海黄兴路干线.xodr
pytessng/Files/Examples/1-路网导入样例：OpenDrive/机动车交叉口.xodr
pytessng/Files/Examples/10-数据导出样例：选区数据/武汉理工路网.json
pytessng/Files/Examples/10-数据导出样例：选区数据/武汉理工路网.tess
pytessng/Files/Examples/11-路网编辑样例/横截面切片测试.tess
pytessng/Files/Examples/2-路网导入样例：Shape/中心线_笛卡尔坐标-上海南浦大道快速路/lane.cpg
pytessng/Files/Examples/2-路网导入样例：Shape/中心线_笛卡尔坐标-上海南浦大道快速路/lane.dbf
pytessng/Files/Examples/2-路网导入样例：Shape/中心线_笛卡尔坐标-上海南浦大道快速路/lane.shp
pytessng/Files/Examples/2-路网导入样例：Shape/中心线_笛卡尔坐标-上海南浦大道快速路/lane.shx
pytessng/Files/Examples/2-路网导入样例：Shape/中心线_笛卡尔坐标-上海南浦大道快速路/laneConnector.cpg
pytessng/Files/Examples/2-路网导入样例：Shape/中心线_笛卡尔坐标-上海南浦大道快速路/laneConnector.dbf
pytessng/Files/Examples/2-路网导入样例：Shape/中心线_笛卡尔坐标-上海南浦大道快速路/laneConnector.shp
pytessng/Files/Examples/2-路网导入样例：Shape/中心线_笛卡尔坐标-上海南浦大道快速路/laneConnector.shx
pytessng/Files/Examples/2-路网导入样例：Shape/中心线_经纬度坐标/lane.cpg
pytessng/Files/Examples/2-路网导入样例：Shape/中心线_经纬度坐标/lane.dbf
pytessng/Files/Examples/2-路网导入样例：Shape/中心线_经纬度坐标/lane.prj
pytessng/Files/Examples/2-路网导入样例：Shape/中心线_经纬度坐标/lane.sbn
pytessng/Files/Examples/2-路网导入样例：Shape/中心线_经纬度坐标/lane.sbx
pytessng/Files/Examples/2-路网导入样例：Shape/中心线_经纬度坐标/lane.shp
pytessng/Files/Examples/2-路网导入样例：Shape/中心线_经纬度坐标/lane.shx
pytessng/Files/Examples/2-路网导入样例：Shape/中心线_经纬度坐标/laneConnector.cpg
pytessng/Files/Examples/2-路网导入样例：Shape/中心线_经纬度坐标/laneConnector.dbf
pytessng/Files/Examples/2-路网导入样例：Shape/中心线_经纬度坐标/laneConnector.prj
pytessng/Files/Examples/2-路网导入样例：Shape/中心线_经纬度坐标/laneConnector.sbn
pytessng/Files/Examples/2-路网导入样例：Shape/中心线_经纬度坐标/laneConnector.sbx
pytessng-0.4.8.dist-info/LICENSE
pytessng-0.4.8.dist-info/METADATA
pytessng-0.4.8.dist-info/WHEEL
pytessng-0.4.8.dist-info/top_level.txt
pytessng-0.4.8.dist-info/RECORD
