Metadata-Version: 2.1
Name: pytessng
Version: 0.4.8
Summary: TESS NG Toolkit for Network Edit
Home-page: https://www.jidatraffic.com/
Author: Xinghao Su
Author-email: 948117072@qq.com
License: UNKNOWN
Platform: UNKNOWN
Classifier: License :: OSI Approved :: MIT License
Classifier: Programming Language :: Python :: 3.6
Classifier: Operating System :: Microsoft :: Windows
Classifier: Topic :: Education :: Computer Aided Instruction (CAI)
Classifier: Topic :: Games/Entertainment :: Simulation
Classifier: Topic :: Software Development :: Libraries :: Python Modules
Requires-Python: ==3.6.*
License-File: LICENSE
Requires-Dist: commonroad-io (==2020.2)
Requires-Dist: dbfread
Requires-Dist: Fiona
Requires-Dist: geopandas
Requires-Dist: kafka-python
Requires-Dist: lxml
Requires-Dist: networkx
Requires-Dist: numpy
Requires-Dist: osmnx
Requires-Dist: pandas
Requires-Dist: Pillow
Requires-Dist: pydantic
Requires-Dist: pyproj
Requires-Dist: pyshp
Requires-Dist: PySide2
Requires-Dist: requests
Requires-Dist: Rtree
Requires-Dist: scipy
Requires-Dist: Shapely
Requires-Dist: singleton-decorator
Requires-Dist: tessng
Requires-Dist: xlrd (==1.2.0)
